hlsorigin/__init__.py
hlsorigin/capture.py
hlsorigin/debug.py
hlsorigin/startover.py
hlsorigin/util.py
hlsorigin-0.0.16.dist-info/DESCRIPTION.rst
hlsorigin-0.0.16.dist-info/METADATA
hlsorigin-0.0.16.dist-info/RECORD
hlsorigin-0.0.16.dist-info/WHEEL
hlsorigin-0.0.16.dist-info/entry_points.txt
hlsorigin-0.0.16.dist-info/metadata.json
hlsorigin-0.0.16.dist-info/top_level.txt
