Metadata-Version: 2.0
Name: hlsorigin
Version: 0.0.16
Summary: Command line tools for HLS manipulation at origin or edge server
Home-page: https://github.com/Eyevinn/hls-origin-scripts
Author: Jonas Birme
Author-email: jonas.birme@eyevinn.se
License: MIT
Platform: UNKNOWN
Requires-Dist: m3u8 (>=0.3.0)
